jenkins_lockable_resources/__init__.py
jenkins_lockable_resources/app.py
jenkins_lockable_resources/config.py
jenkins_lockable_resources/main.py
jenkins_lockable_resources/model.py
jenkins_lockable_resources-1.2.1.dist-info/licenses/LICENSE.txt
jenkins_lockable_resources-1.2.1.dist-info/METADATA
jenkins_lockable_resources-1.2.1.dist-info/WHEEL
jenkins_lockable_resources-1.2.1.dist-info/entry_points.txt
jenkins_lockable_resources-1.2.1.dist-info/top_level.txt
jenkins_lockable_resources-1.2.1.dist-info/RECORD
