Metadata-Version: 2.4
Name: jenkins-lockable-resources
Version: 1.2.1
Summary: A Python API for accessing lockable resources from Jenkins lockable-resources plugin.
Home-page: https://gitlab.com/alexandre-perrin1/jenkins-lockable-resources
Author: Alexandre Perrin
Author-email: alexandreperr@gmail.com
License: MIT
Classifier: Environment :: Console
Classifier: Intended Audience :: Developers
Classifier: Intended Audience :: Information Technology
Classifier: Intended Audience :: System Administrators
Classifier: Natural Language :: English
Classifier: Operating System :: OS Independent
Classifier: Operating System :: OS Independent
Classifier: Programming Language :: Python
Classifier: Programming Language :: Python :: 3
Classifier: Programming Language :: Python :: 3.6
Classifier: Programming Language :: Python :: 3.7
Classifier: Programming Language :: Python :: 3.8
Classifier: Topic :: Software Development :: Testing
Classifier: Topic :: Utilities
License-File: LICENSE.txt
Requires-Dist: click~=7.0
Requires-Dist: jenkinsapi~=0.3
Requires-Dist: requests~=2.24
Requires-Dist: PyYaml~=6.0
Dynamic: license-file
